{"nm":"Motion 4_Lottie Delivery","ddd":0,"h":256,"w":256,"meta":{"g":"LottieFiles AE 1.0.0"},"layers":[{"ty":4,"nm":"Bar 3","sr":1,"st":0,"op":122,"ip":0,"hd":false,"ddd":0,"bm":0,"hasMask":false,"ao":0,"ks":{"a":{"a":0,"k":[128,160.094,0],"ix":1},"s":{"a":0,"k":[100,100,100],"ix":6},"sk":{"a":0,"k":0},"p":{"a":0,"k":[128,160.094,0],"ix":2},"r":{"a":0,"k":0,"ix":10},"sa":{"a":0,"k":0},"o":{"a":0,"k":100,"ix":11}},"ef":[],"shapes":[{"ty":"gr","bm":0,"hd":false,"mn":"ADBE Vector Group","nm":"Top","ix":1,"cix":2,"np":3,"it":[{"ty":"sh","bm":0,"hd":false,"mn":"ADBE Vector Shape - Group","nm":"Path 1","ix":1,"d":1,"ks":{"a":1,"k":[{"o":{"x":0.8,"y":0},"i":{"x":0.2,"y":1},"s":[{"c":true,"i":[[0,0],[0,0],[0,0],[0,0]],"o":[[0,0],[0,0],[0,0],[0,0]],"v":[[128,167.188],[107.216,155.188],[128,143.188],[148.785,155.188]]}],"t":0},{"o":{"x":0.8,"y":0},"i":{"x":0.2,"y":1},"s":[{"c":true,"i":[[0,0],[0,0],[0,0],[0,0]],"o":[[0,0],[0,0],[0,0],[0,0]],"v":[[128.14,134.939],[107.355,122.939],[128.14,110.939],[148.924,122.939]]}],"t":30},{"o":{"x":0.8,"y":0},"i":{"x":0.2,"y":1},"s":[{"c":true,"i":[[0,0],[0,0],[0,0],[0,0]],"o":[[0,0],[0,0],[0,0],[0,0]],"v":[[127.794,151.938],[107.009,139.938],[127.794,127.938],[148.578,139.938]]}],"t":60},{"o":{"x":0.8,"y":0},"i":{"x":0.2,"y":1},"s":[{"c":true,"i":[[0,0],[0,0],[0,0],[0,0]],"o":[[0,0],[0,0],[0,0],[0,0]],"v":[[128.002,145.939],[107.217,133.939],[128.002,121.939],[148.787,133.939]]}],"t":90},{"s":[{"c":true,"i":[[0,0],[0,0],[0,0],[0,0]],"o":[[0,0],[0,0],[0,0],[0,0]],"v":[[128,167.188],[107.216,155.188],[128,143.188],[148.785,155.188]]}],"t":120}],"ix":2}},{"ty":"st","bm":0,"hd":false,"mn":"ADBE Vector Graphic - Stroke","nm":"Stroke 1","lc":1,"lj":2,"ml":1,"o":{"a":0,"k":100,"ix":4},"w":{"a":0,"k":3,"ix":5},"c":{"a":0,"k":[0.1608,0.6784,0.3922],"ix":3}},{"ty":"fl","bm":0,"hd":false,"mn":"ADBE Vector Graphic - Fill","nm":"Fill 1","c":{"a":0,"k":[1,1,1],"ix":4},"r":1,"o":{"a":0,"k":100,"ix":5}},{"ty":"tr","a":{"a":0,"k":[0,0],"ix":1},"s":{"a":0,"k":[100,100],"ix":3},"sk":{"a":0,"k":0,"ix":4},"p":{"a":0,"k":[0,0],"ix":2},"r":{"a":0,"k":0,"ix":6},"sa":{"a":0,"k":0,"ix":5},"o":{"a":0,"k":100,"ix":7}}]},{"ty":"gr","bm":0,"hd":false,"mn":"ADBE Vector Group","nm":"Side","ix":2,"cix":2,"np":3,"it":[{"ty":"sh","bm":0,"hd":false,"mn":"ADBE Vector Shape - Group","nm":"Path 1","ix":1,"d":1,"ks":{"a":1,"k":[{"o":{"x":0.8,"y":0},"i":{"x":0.2,"y":1},"s":[{"c":true,"i":[[0,0],[0,0],[0,0],[0,0]],"o":[[0,0],[0,0],[0,0],[0,0]],"v":[[128,176],[107.216,164],[107.216,155.188],[128,167.188]]}],"t":0},{"o":{"x":0.8,"y":0},"i":{"x":0.2,"y":1},"s":[{"c":true,"i":[[0,0],[0,0],[0,0],[0,0]],"o":[[0,0],[0,0],[0,0],[0,0]],"v":[[128,176],[107.216,164],[107.355,122.939],[128.14,134.939]]}],"t":30},{"o":{"x":0.8,"y":0},"i":{"x":0.2,"y":1},"s":[{"c":true,"i":[[0,0],[0,0],[0,0],[0,0]],"o":[[0,0],[0,0],[0,0],[0,0]],"v":[[128,176],[107.216,164],[107.009,139.938],[127.794,151.938]]}],"t":60},{"o":{"x":0.8,"y":0},"i":{"x":0.2,"y":1},"s":[{"c":true,"i":[[0,0],[0,0],[0,0],[0,0]],"o":[[0,0],[0,0],[0,0],[0,0]],"v":[[128,176],[107.216,164],[107.217,133.939],[128.002,145.939]]}],"t":90},{"s":[{"c":true,"i":[[0,0],[0,0],[0,0],[0,0]],"o":[[0,0],[0,0],[0,0],[0,0]],"v":[[128,176],[107.216,164],[107.216,155.188],[128,167.188]]}],"t":120}],"ix":2}},{"ty":"st","bm":0,"hd":false,"mn":"ADBE Vector Graphic - Stroke","nm":"Stroke 1","lc":1,"lj":2,"ml":1,"o":{"a":0,"k":100,"ix":4},"w":{"a":0,"k":3,"ix":5},"c":{"a":0,"k":[0.1608,0.6784,0.3922],"ix":3}},{"ty":"fl","bm":0,"hd":false,"mn":"ADBE Vector Graphic - Fill","nm":"Fill 1","c":{"a":0,"k":[1,1,1],"ix":4},"r":1,"o":{"a":0,"k":100,"ix":5}},{"ty":"tr","a":{"a":0,"k":[0,0],"ix":1},"s":{"a":0,"k":[100,100],"ix":3},"sk":{"a":0,"k":0,"ix":4},"p":{"a":0,"k":[0,0],"ix":2},"r":{"a":0,"k":0,"ix":6},"sa":{"a":0,"k":0,"ix":5},"o":{"a":0,"k":100,"ix":7}}]},{"ty":"gr","bm":0,"hd":false,"mn":"ADBE Vector Group","nm":"Front","ix":3,"cix":2,"np":3,"it":[{"ty":"sh","bm":0,"hd":false,"mn":"ADBE Vector Shape - Group","nm":"Path 1","ix":1,"d":1,"ks":{"a":1,"k":[{"o":{"x":0.8,"y":0},"i":{"x":0.2,"y":1},"s":[{"c":true,"i":[[0,0],[0,0],[0,0],[0,0]],"o":[[0,0],[0,0],[0,0],[0,0]],"v":[[148.785,164],[128,176],[128,167.188],[148.785,155.188]]}],"t":0},{"o":{"x":0.8,"y":0},"i":{"x":0.2,"y":1},"s":[{"c":true,"i":[[0,0],[0,0],[0,0],[0,0]],"o":[[0,0],[0,0],[0,0],[0,0]],"v":[[148.785,164],[128,176],[128.14,134.939],[148.924,122.939]]}],"t":30},{"o":{"x":0.8,"y":0},"i":{"x":0.2,"y":1},"s":[{"c":true,"i":[[0,0],[0,0],[0,0],[0,0]],"o":[[0,0],[0,0],[0,0],[0,0]],"v":[[148.785,164],[128,176],[127.794,151.938],[148.578,139.938]]}],"t":60},{"o":{"x":0.8,"y":0},"i":{"x":0.2,"y":1},"s":[{"c":true,"i":[[0,0],[0,0],[0,0],[0,0]],"o":[[0,0],[0,0],[0,0],[0,0]],"v":[[148.785,164],[128,176],[128.002,145.939],[148.787,133.939]]}],"t":90},{"s":[{"c":true,"i":[[0,0],[0,0],[0,0],[0,0]],"o":[[0,0],[0,0],[0,0],[0,0]],"v":[[148.785,164],[128,176],[128,167.188],[148.785,155.188]]}],"t":120}],"ix":2}},{"ty":"st","bm":0,"hd":false,"mn":"ADBE Vector Graphic - Stroke","nm":"Stroke 1","lc":1,"lj":2,"ml":1,"o":{"a":0,"k":100,"ix":4},"w":{"a":0,"k":3,"ix":5},"c":{"a":0,"k":[0.1608,0.6784,0.3922],"ix":3}},{"ty":"fl","bm":0,"hd":false,"mn":"ADBE Vector Graphic - Fill","nm":"Fill 1","c":{"a":0,"k":[1,1,1],"ix":4},"r":1,"o":{"a":0,"k":100,"ix":5}},{"ty":"tr","a":{"a":0,"k":[0,0],"ix":1},"s":{"a":0,"k":[100,100],"ix":3},"sk":{"a":0,"k":0,"ix":4},"p":{"a":0,"k":[0,0],"ix":2},"r":{"a":0,"k":0,"ix":6},"sa":{"a":0,"k":0,"ix":5},"o":{"a":0,"k":100,"ix":7}}]}],"ind":1},{"ty":4,"nm":"Bar 4","sr":1,"st":0,"op":122,"ip":0,"hd":false,"ddd":0,"bm":0,"hasMask":false,"ao":0,"ks":{"a":{"a":0,"k":[148.785,144.189,0],"ix":1},"s":{"a":0,"k":[100,100,100],"ix":6},"sk":{"a":0,"k":0},"p":{"a":0,"k":[148.785,144.189,0],"ix":2},"r":{"a":0,"k":0,"ix":10},"sa":{"a":0,"k":0},"o":{"a":0,"k":100,"ix":11}},"ef":[],"shapes":[{"ty":"gr","bm":0,"hd":false,"mn":"ADBE Vector Group","nm":"Top","ix":1,"cix":2,"np":3,"it":[{"ty":"sh","bm":0,"hd":false,"mn":"ADBE Vector Shape - Group","nm":"Path 1","ix":1,"d":1,"ks":{"a":1,"k":[{"o":{"x":0.8,"y":0},"i":{"x":0.2,"y":1},"s":[{"c":true,"i":[[0,0],[0,0],[0,0],[0,0]],"o":[[0,0],[0,0],[0,0],[0,0]],"v":[[148.889,144.128],[128.104,132.128],[148.889,120.128],[169.673,132.128]]}],"t":0},{"o":{"x":0.8,"y":0},"i":{"x":0.2,"y":1},"s":[{"c":true,"i":[[0,0],[0,0],[0,0],[0,0]],"o":[[0,0],[0,0],[0,0],[0,0]],"v":[[148.487,141.003],[127.703,129.003],[148.487,117.003],[169.272,129.003]]}],"t":30},{"o":{"x":0.8,"y":0},"i":{"x":0.2,"y":1},"s":[{"c":true,"i":[[0,0],[0,0],[0,0],[0,0]],"o":[[0,0],[0,0],[0,0],[0,0]],"v":[[148.778,128.003],[127.994,116.003],[148.778,104.003],[169.563,116.003]]}],"t":60},{"o":{"x":0.8,"y":0},"i":{"x":0.2,"y":1},"s":[{"c":true,"i":[[0,0],[0,0],[0,0],[0,0]],"o":[[0,0],[0,0],[0,0],[0,0]],"v":[[148.807,111.003],[128.022,99.003],[148.807,87.003],[169.591,99.003]]}],"t":90},{"s":[{"c":true,"i":[[0,0],[0,0],[0,0],[0,0]],"o":[[0,0],[0,0],[0,0],[0,0]],"v":[[148.889,144.128],[128.104,132.128],[148.889,120.128],[169.673,132.128]]}],"t":120}],"ix":2}},{"ty":"st","bm":0,"hd":false,"mn":"ADBE Vector Graphic - Stroke","nm":"Stroke 1","lc":1,"lj":2,"ml":1,"o":{"a":0,"k":100,"ix":4},"w":{"a":0,"k":3,"ix":5},"c":{"a":0,"k":[0.1608,0.6784,0.3922],"ix":3}},{"ty":"fl","bm":0,"hd":false,"mn":"ADBE Vector Graphic - Fill","nm":"Fill 1","c":{"a":0,"k":[1,1,1],"ix":4},"r":1,"o":{"a":0,"k":100,"ix":5}},{"ty":"tr","a":{"a":0,"k":[0,0],"ix":1},"s":{"a":0,"k":[100,100],"ix":3},"sk":{"a":0,"k":0,"ix":4},"p":{"a":0,"k":[0,0],"ix":2},"r":{"a":0,"k":0,"ix":6},"sa":{"a":0,"k":0,"ix":5},"o":{"a":0,"k":100,"ix":7}}]},{"ty":"gr","bm":0,"hd":false,"mn":"ADBE Vector Group","nm":"Side","ix":2,"cix":2,"np":3,"it":[{"ty":"sh","bm":0,"hd":false,"mn":"ADBE Vector Shape - Group","nm":"Path 1","ix":1,"d":1,"ks":{"a":1,"k":[{"o":{"x":0.8,"y":0},"i":{"x":0.2,"y":1},"s":[{"c":true,"i":[[0,0],[0,0],[0,0],[0,0]],"o":[[0,0],[0,0],[0,0],[0,0]],"v":[[148.785,164],[128,152],[128.104,132.128],[148.889,144.128]]}],"t":0},{"o":{"x":0.8,"y":0},"i":{"x":0.2,"y":1},"s":[{"c":true,"i":[[0,0],[0,0],[0,0],[0,0]],"o":[[0,0],[0,0],[0,0],[0,0]],"v":[[148.785,164],[128,152],[127.702,129.003],[148.487,141.003]]}],"t":30},{"o":{"x":0.8,"y":0},"i":{"x":0.2,"y":1},"s":[{"c":true,"i":[[0,0],[0,0],[0,0],[0,0]],"o":[[0,0],[0,0],[0,0],[0,0]],"v":[[148.785,164],[128,152],[127.994,116.003],[148.778,128.003]]}],"t":60},{"o":{"x":0.8,"y":0},"i":{"x":0.2,"y":1},"s":[{"c":true,"i":[[0,0],[0,0],[0,0],[0,0]],"o":[[0,0],[0,0],[0,0],[0,0]],"v":[[148.785,164],[128,152],[128.022,99.003],[148.807,111.003]]}],"t":90},{"s":[{"c":true,"i":[[0,0],[0,0],[0,0],[0,0]],"o":[[0,0],[0,0],[0,0],[0,0]],"v":[[148.785,164],[128,152],[128.104,132.128],[148.889,144.128]]}],"t":120}],"ix":2}},{"ty":"st","bm":0,"hd":false,"mn":"ADBE Vector Graphic - Stroke","nm":"Stroke 1","lc":1,"lj":2,"ml":1,"o":{"a":0,"k":100,"ix":4},"w":{"a":0,"k":3,"ix":5},"c":{"a":0,"k":[0.1608,0.6784,0.3922],"ix":3}},{"ty":"fl","bm":0,"hd":false,"mn":"ADBE Vector Graphic - Fill","nm":"Fill 1","c":{"a":0,"k":[1,1,1],"ix":4},"r":1,"o":{"a":0,"k":100,"ix":5}},{"ty":"tr","a":{"a":0,"k":[0,0],"ix":1},"s":{"a":0,"k":[100,100],"ix":3},"sk":{"a":0,"k":0,"ix":4},"p":{"a":0,"k":[0,0],"ix":2},"r":{"a":0,"k":0,"ix":6},"sa":{"a":0,"k":0,"ix":5},"o":{"a":0,"k":100,"ix":7}}]},{"ty":"gr","bm":0,"hd":false,"mn":"ADBE Vector Group","nm":"Front","ix":3,"cix":2,"np":3,"it":[{"ty":"sh","bm":0,"hd":false,"mn":"ADBE Vector Shape - Group","nm":"Path 1","ix":1,"d":1,"ks":{"a":1,"k":[{"o":{"x":0.8,"y":0},"i":{"x":0.2,"y":1},"s":[{"c":true,"i":[[0,0],[0,0],[0,0],[0,0]],"o":[[0,0],[0,0],[0,0],[0,0]],"v":[[169.569,152],[148.785,164],[148.889,144.128],[169.673,132.128]]}],"t":0},{"o":{"x":0.8,"y":0},"i":{"x":0.2,"y":1},"s":[{"c":true,"i":[[0,0],[0,0],[0,0],[0,0]],"o":[[0,0],[0,0],[0,0],[0,0]],"v":[[169.569,152],[148.785,164],[148.487,141.003],[169.272,129.003]]}],"t":30},{"o":{"x":0.8,"y":0},"i":{"x":0.2,"y":1},"s":[{"c":true,"i":[[0,0],[0,0],[0,0],[0,0]],"o":[[0,0],[0,0],[0,0],[0,0]],"v":[[169.569,152],[148.785,164],[148.778,128.003],[169.563,116.003]]}],"t":60},{"o":{"x":0.8,"y":0},"i":{"x":0.2,"y":1},"s":[{"c":true,"i":[[0,0],[0,0],[0,0],[0,0]],"o":[[0,0],[0,0],[0,0],[0,0]],"v":[[169.569,152],[148.785,164],[148.807,111.003],[169.591,99.003]]}],"t":90},{"s":[{"c":true,"i":[[0,0],[0,0],[0,0],[0,0]],"o":[[0,0],[0,0],[0,0],[0,0]],"v":[[169.569,152],[148.785,164],[148.889,144.128],[169.673,132.128]]}],"t":120}],"ix":2}},{"ty":"st","bm":0,"hd":false,"mn":"ADBE Vector Graphic - Stroke","nm":"Stroke 1","lc":1,"lj":2,"ml":1,"o":{"a":0,"k":100,"ix":4},"w":{"a":0,"k":3,"ix":5},"c":{"a":0,"k":[0.1608,0.6784,0.3922],"ix":3}},{"ty":"fl","bm":0,"hd":false,"mn":"ADBE Vector Graphic - Fill","nm":"Fill 1","c":{"a":0,"k":[1,1,1],"ix":4},"r":1,"o":{"a":0,"k":100,"ix":5}},{"ty":"tr","a":{"a":0,"k":[0,0],"ix":1},"s":{"a":0,"k":[100,100],"ix":3},"sk":{"a":0,"k":0,"ix":4},"p":{"a":0,"k":[0,0],"ix":2},"r":{"a":0,"k":0,"ix":6},"sa":{"a":0,"k":0,"ix":5},"o":{"a":0,"k":100,"ix":7}}]}],"ind":2},{"ty":4,"nm":"Bar 2","sr":1,"st":0,"op":122,"ip":0,"hd":false,"ddd":0,"bm":0,"hasMask":false,"ao":0,"ks":{"a":{"a":0,"k":[107.216,137,0],"ix":1},"s":{"a":0,"k":[100,100,100],"ix":6},"sk":{"a":0,"k":0},"p":{"a":0,"k":[107.216,137,0],"ix":2},"r":{"a":0,"k":0,"ix":10},"sa":{"a":0,"k":0},"o":{"a":0,"k":100,"ix":11}},"ef":[],"shapes":[{"ty":"gr","bm":0,"hd":false,"mn":"ADBE Vector Group","nm":"Top","ix":1,"cix":2,"np":3,"it":[{"ty":"sh","bm":0,"hd":false,"mn":"ADBE Vector Shape - Group","nm":"Path 1","ix":1,"d":1,"ks":{"a":1,"k":[{"o":{"x":0.8,"y":0},"i":{"x":0.2,"y":1},"s":[{"c":true,"i":[[0,0],[0,0],[0,0],[0,0]],"o":[[0,0],[0,0],[0,0],[0,0]],"v":[[107.216,134],[86.431,122],[107.216,110],[128,122]]}],"t":0},{"o":{"x":0.8,"y":0},"i":{"x":0.2,"y":1},"s":[{"c":true,"i":[[0,0],[0,0],[0,0],[0,0]],"o":[[0,0],[0,0],[0,0],[0,0]],"v":[[107.305,152.125],[86.52,140.125],[107.305,128.125],[128.089,140.125]]}],"t":30},{"o":{"x":0.8,"y":0},"i":{"x":0.2,"y":1},"s":[{"c":true,"i":[[0,0],[0,0],[0,0],[0,0]],"o":[[0,0],[0,0],[0,0],[0,0]],"v":[[107.182,111.125],[86.397,99.125],[107.182,87.125],[127.966,99.125]]}],"t":60},{"o":{"x":0.8,"y":0},"i":{"x":0.2,"y":1},"s":[{"c":true,"i":[[0,0],[0,0],[0,0],[0,0]],"o":[[0,0],[0,0],[0,0],[0,0]],"v":[[107.206,152],[86.421,140],[107.206,128],[127.991,140]]}],"t":90},{"s":[{"c":true,"i":[[0,0],[0,0],[0,0],[0,0]],"o":[[0,0],[0,0],[0,0],[0,0]],"v":[[107.216,134],[86.431,122],[107.216,110],[128,122]]}],"t":120}],"ix":2}},{"ty":"st","bm":0,"hd":false,"mn":"ADBE Vector Graphic - Stroke","nm":"Stroke 1","lc":1,"lj":2,"ml":1,"o":{"a":0,"k":100,"ix":4},"w":{"a":0,"k":3,"ix":5},"c":{"a":0,"k":[0.1608,0.6784,0.3922],"ix":3}},{"ty":"fl","bm":0,"hd":false,"mn":"ADBE Vector Graphic - Fill","nm":"Fill 1","c":{"a":0,"k":[1,1,1],"ix":4},"r":1,"o":{"a":0,"k":100,"ix":5}},{"ty":"tr","a":{"a":0,"k":[0,0],"ix":1},"s":{"a":0,"k":[100,100],"ix":3},"sk":{"a":0,"k":0,"ix":4},"p":{"a":0,"k":[0,0],"ix":2},"r":{"a":0,"k":0,"ix":6},"sa":{"a":0,"k":0,"ix":5},"o":{"a":0,"k":100,"ix":7}}]},{"ty":"gr","bm":0,"hd":false,"mn":"ADBE Vector Group","nm":"Side","ix":2,"cix":2,"np":3,"it":[{"ty":"sh","bm":0,"hd":false,"mn":"ADBE Vector Shape - Group","nm":"Path 1","ix":1,"d":1,"ks":{"a":1,"k":[{"o":{"x":0.8,"y":0},"i":{"x":0.2,"y":1},"s":[{"c":true,"i":[[0,0],[0,0],[0,0],[0,0]],"o":[[0,0],[0,0],[0,0],[0,0]],"v":[[107.216,164],[86.431,152],[86.431,122],[107.216,134]]}],"t":0},{"o":{"x":0.8,"y":0},"i":{"x":0.2,"y":1},"s":[{"c":true,"i":[[0,0],[0,0],[0,0],[0,0]],"o":[[0,0],[0,0],[0,0],[0,0]],"v":[[107.216,164],[86.431,152],[86.52,140.125],[107.305,152.125]]}],"t":30},{"o":{"x":0.8,"y":0},"i":{"x":0.2,"y":1},"s":[{"c":true,"i":[[0,0],[0,0],[0,0],[0,0]],"o":[[0,0],[0,0],[0,0],[0,0]],"v":[[107.216,164],[86.431,152],[86.397,99.125],[107.182,111.125]]}],"t":60},{"o":{"x":0.8,"y":0},"i":{"x":0.2,"y":1},"s":[{"c":true,"i":[[0,0],[0,0],[0,0],[0,0]],"o":[[0,0],[0,0],[0,0],[0,0]],"v":[[107.216,164],[86.431,152],[86.421,140],[107.206,152]]}],"t":90},{"s":[{"c":true,"i":[[0,0],[0,0],[0,0],[0,0]],"o":[[0,0],[0,0],[0,0],[0,0]],"v":[[107.216,164],[86.431,152],[86.431,122],[107.216,134]]}],"t":120}],"ix":2}},{"ty":"st","bm":0,"hd":false,"mn":"ADBE Vector Graphic - Stroke","nm":"Stroke 1","lc":1,"lj":2,"ml":1,"o":{"a":0,"k":100,"ix":4},"w":{"a":0,"k":3,"ix":5},"c":{"a":0,"k":[0.1608,0.6784,0.3922],"ix":3}},{"ty":"fl","bm":0,"hd":false,"mn":"ADBE Vector Graphic - Fill","nm":"Fill 1","c":{"a":0,"k":[1,1,1],"ix":4},"r":1,"o":{"a":0,"k":100,"ix":5}},{"ty":"tr","a":{"a":0,"k":[0,0],"ix":1},"s":{"a":0,"k":[100,100],"ix":3},"sk":{"a":0,"k":0,"ix":4},"p":{"a":0,"k":[0,0],"ix":2},"r":{"a":0,"k":0,"ix":6},"sa":{"a":0,"k":0,"ix":5},"o":{"a":0,"k":100,"ix":7}}]},{"ty":"gr","bm":0,"hd":false,"mn":"ADBE Vector Group","nm":"Front","ix":3,"cix":2,"np":3,"it":[{"ty":"sh","bm":0,"hd":false,"mn":"ADBE Vector Shape - Group","nm":"Path 1","ix":1,"d":1,"ks":{"a":1,"k":[{"o":{"x":0.8,"y":0},"i":{"x":0.2,"y":1},"s":[{"c":true,"i":[[0,0],[0,0],[0,0],[0,0]],"o":[[0,0],[0,0],[0,0],[0,0]],"v":[[128,152],[107.216,164],[107.216,134],[128,122]]}],"t":0},{"o":{"x":0.8,"y":0},"i":{"x":0.2,"y":1},"s":[{"c":true,"i":[[0,0],[0,0],[0,0],[0,0]],"o":[[0,0],[0,0],[0,0],[0,0]],"v":[[128,152],[107.216,164],[107.305,152.125],[128.089,140.125]]}],"t":30},{"o":{"x":0.8,"y":0},"i":{"x":0.2,"y":1},"s":[{"c":true,"i":[[0,0],[0,0],[0,0],[0,0]],"o":[[0,0],[0,0],[0,0],[0,0]],"v":[[128,152],[107.216,164],[107.182,111.125],[127.967,99.125]]}],"t":60},{"o":{"x":0.8,"y":0},"i":{"x":0.2,"y":1},"s":[{"c":true,"i":[[0,0],[0,0],[0,0],[0,0]],"o":[[0,0],[0,0],[0,0],[0,0]],"v":[[128,152],[107.216,164],[107.206,152],[127.991,140]]}],"t":90},{"s":[{"c":true,"i":[[0,0],[0,0],[0,0],[0,0]],"o":[[0,0],[0,0],[0,0],[0,0]],"v":[[128,152],[107.216,164],[107.216,134],[128,122]]}],"t":120}],"ix":2}},{"ty":"st","bm":0,"hd":false,"mn":"ADBE Vector Graphic - Stroke","nm":"Stroke 1","lc":1,"lj":2,"ml":1,"o":{"a":0,"k":100,"ix":4},"w":{"a":0,"k":3,"ix":5},"c":{"a":0,"k":[0.1608,0.6784,0.3922],"ix":3}},{"ty":"fl","bm":0,"hd":false,"mn":"ADBE Vector Graphic - Fill","nm":"Fill 1","c":{"a":0,"k":[1,1,1],"ix":4},"r":1,"o":{"a":0,"k":100,"ix":5}},{"ty":"tr","a":{"a":0,"k":[0,0],"ix":1},"s":{"a":0,"k":[100,100],"ix":3},"sk":{"a":0,"k":0,"ix":4},"p":{"a":0,"k":[0,0],"ix":2},"r":{"a":0,"k":0,"ix":6},"sa":{"a":0,"k":0,"ix":5},"o":{"a":0,"k":100,"ix":7}}]}],"ind":3},{"ty":4,"nm":"Bar 1","sr":1,"st":0,"op":122,"ip":0,"hd":false,"ddd":0,"bm":0,"hasMask":false,"ao":0,"ks":{"a":{"a":0,"k":[128,116,0],"ix":1},"s":{"a":0,"k":[100,100,100],"ix":6},"sk":{"a":0,"k":0},"p":{"a":0,"k":[128,116,0],"ix":2},"r":{"a":0,"k":0,"ix":10},"sa":{"a":0,"k":0},"o":{"a":0,"k":100,"ix":11}},"ef":[],"shapes":[{"ty":"gr","bm":0,"hd":false,"mn":"ADBE Vector Group","nm":"Top","ix":1,"cix":2,"np":3,"it":[{"ty":"sh","bm":0,"hd":false,"mn":"ADBE Vector Shape - Group","nm":"Path 1","ix":1,"d":1,"ks":{"a":1,"k":[{"o":{"x":0.8,"y":0},"i":{"x":0.2,"y":1},"s":[{"c":true,"i":[[0,0],[0,0],[0,0],[0,0]],"o":[[0,0],[0,0],[0,0],[0,0]],"v":[[128,104],[107.215,92],[128,80],[148.785,92]]}],"t":0},{"o":{"x":0.8,"y":0},"i":{"x":0.2,"y":1},"s":[{"c":true,"i":[[0,0],[0,0],[0,0],[0,0]],"o":[[0,0],[0,0],[0,0],[0,0]],"v":[[128,120.312],[107.215,108.312],[128,96.312],[148.785,108.312]]}],"t":30},{"o":{"x":0.8,"y":0},"i":{"x":0.2,"y":1},"s":[{"c":true,"i":[[0,0],[0,0],[0,0],[0,0]],"o":[[0,0],[0,0],[0,0],[0,0]],"v":[[127.889,126.937],[107.104,114.937],[127.889,102.938],[148.674,114.938]]}],"t":60},{"o":{"x":0.8,"y":0},"i":{"x":0.2,"y":1},"s":[{"c":true,"i":[[0,0],[0,0],[0,0],[0,0]],"o":[[0,0],[0,0],[0,0],[0,0]],"v":[[127.778,115.937],[106.993,103.937],[127.778,91.938],[148.562,103.938]]}],"t":90},{"s":[{"c":true,"i":[[0,0],[0,0],[0,0],[0,0]],"o":[[0,0],[0,0],[0,0],[0,0]],"v":[[128,104],[107.215,92],[128,80],[148.785,92]]}],"t":120}],"ix":2}},{"ty":"st","bm":0,"hd":false,"mn":"ADBE Vector Graphic - Stroke","nm":"Stroke 1","lc":1,"lj":2,"ml":1,"o":{"a":0,"k":100,"ix":4},"w":{"a":0,"k":3,"ix":5},"c":{"a":0,"k":[0.1608,0.6784,0.3922],"ix":3}},{"ty":"fl","bm":0,"hd":false,"mn":"ADBE Vector Graphic - Fill","nm":"Fill 1","c":{"a":0,"k":[1,1,1],"ix":4},"r":1,"o":{"a":0,"k":100,"ix":5}},{"ty":"tr","a":{"a":0,"k":[0,0],"ix":1},"s":{"a":0,"k":[100,100],"ix":3},"sk":{"a":0,"k":0,"ix":4},"p":{"a":0,"k":[0,0],"ix":2},"r":{"a":0,"k":0,"ix":6},"sa":{"a":0,"k":0,"ix":5},"o":{"a":0,"k":100,"ix":7}}]},{"ty":"gr","bm":0,"hd":false,"mn":"ADBE Vector Group","nm":"Side","ix":2,"cix":2,"np":3,"it":[{"ty":"sh","bm":0,"hd":false,"mn":"ADBE Vector Shape - Group","nm":"Path 1","ix":1,"d":1,"ks":{"a":1,"k":[{"o":{"x":0.8,"y":0},"i":{"x":0.2,"y":1},"s":[{"c":true,"i":[[0,0],[0,0],[0,0],[0,0]],"o":[[0,0],[0,0],[0,0],[0,0]],"v":[[128,152],[107.215,140],[107.215,92],[128,104]]}],"t":0},{"o":{"x":0.8,"y":0},"i":{"x":0.2,"y":1},"s":[{"c":true,"i":[[0,0],[0,0],[0,0],[0,0]],"o":[[0,0],[0,0],[0,0],[0,0]],"v":[[128,152],[107.215,140],[107.216,108.312],[128,120.312]]}],"t":30},{"o":{"x":0.8,"y":0},"i":{"x":0.2,"y":1},"s":[{"c":true,"i":[[0,0],[0,0],[0,0],[0,0]],"o":[[0,0],[0,0],[0,0],[0,0]],"v":[[128,152],[107.215,140],[107.104,114.937],[127.889,126.937]]}],"t":60},{"o":{"x":0.8,"y":0},"i":{"x":0.2,"y":1},"s":[{"c":true,"i":[[0,0],[0,0],[0,0],[0,0]],"o":[[0,0],[0,0],[0,0],[0,0]],"v":[[128,152],[107.215,140],[106.993,103.937],[127.778,115.937]]}],"t":90},{"s":[{"c":true,"i":[[0,0],[0,0],[0,0],[0,0]],"o":[[0,0],[0,0],[0,0],[0,0]],"v":[[128,152],[107.215,140],[107.215,92],[128,104]]}],"t":120}],"ix":2}},{"ty":"st","bm":0,"hd":false,"mn":"ADBE Vector Graphic - Stroke","nm":"Stroke 1","lc":1,"lj":2,"ml":1,"o":{"a":0,"k":100,"ix":4},"w":{"a":0,"k":3,"ix":5},"c":{"a":0,"k":[0.1608,0.6784,0.3922],"ix":3}},{"ty":"fl","bm":0,"hd":false,"mn":"ADBE Vector Graphic - Fill","nm":"Fill 1","c":{"a":0,"k":[1,1,1],"ix":4},"r":1,"o":{"a":0,"k":100,"ix":5}},{"ty":"tr","a":{"a":0,"k":[0,0],"ix":1},"s":{"a":0,"k":[100,100],"ix":3},"sk":{"a":0,"k":0,"ix":4},"p":{"a":0,"k":[0,0],"ix":2},"r":{"a":0,"k":0,"ix":6},"sa":{"a":0,"k":0,"ix":5},"o":{"a":0,"k":100,"ix":7}}]},{"ty":"gr","bm":0,"hd":false,"mn":"ADBE Vector Group","nm":"Front","ix":3,"cix":2,"np":3,"it":[{"ty":"sh","bm":0,"hd":false,"mn":"ADBE Vector Shape - Group","nm":"Path 1","ix":1,"d":1,"ks":{"a":1,"k":[{"o":{"x":0.8,"y":0},"i":{"x":0.2,"y":1},"s":[{"c":true,"i":[[0,0],[0,0],[0,0],[0,0]],"o":[[0,0],[0,0],[0,0],[0,0]],"v":[[148.785,140],[128,152],[128,104],[148.785,92]]}],"t":0},{"o":{"x":0.8,"y":0},"i":{"x":0.2,"y":1},"s":[{"c":true,"i":[[0,0],[0,0],[0,0],[0,0]],"o":[[0,0],[0,0],[0,0],[0,0]],"v":[[148.785,140],[128,152],[128,120.312],[148.785,108.312]]}],"t":30},{"o":{"x":0.8,"y":0},"i":{"x":0.2,"y":1},"s":[{"c":true,"i":[[0,0],[0,0],[0,0],[0,0]],"o":[[0,0],[0,0],[0,0],[0,0]],"v":[[148.785,140],[128,152],[127.889,126.937],[148.673,114.937]]}],"t":60},{"o":{"x":0.8,"y":0},"i":{"x":0.2,"y":1},"s":[{"c":true,"i":[[0,0],[0,0],[0,0],[0,0]],"o":[[0,0],[0,0],[0,0],[0,0]],"v":[[148.785,140],[128,152],[127.778,115.937],[148.562,103.937]]}],"t":90},{"s":[{"c":true,"i":[[0,0],[0,0],[0,0],[0,0]],"o":[[0,0],[0,0],[0,0],[0,0]],"v":[[148.785,140],[128,152],[128,104],[148.785,92]]}],"t":120}],"ix":2}},{"ty":"st","bm":0,"hd":false,"mn":"ADBE Vector Graphic - Stroke","nm":"Stroke 1","lc":1,"lj":2,"ml":1,"o":{"a":0,"k":100,"ix":4},"w":{"a":0,"k":3,"ix":5},"c":{"a":0,"k":[0.1608,0.6784,0.3922],"ix":3}},{"ty":"fl","bm":0,"hd":false,"mn":"ADBE Vector Graphic - Fill","nm":"Fill 1","c":{"a":0,"k":[1,1,1],"ix":4},"r":1,"o":{"a":0,"k":100,"ix":5}},{"ty":"tr","a":{"a":0,"k":[0,0],"ix":1},"s":{"a":0,"k":[100,100],"ix":3},"sk":{"a":0,"k":0,"ix":4},"p":{"a":0,"k":[0,0],"ix":2},"r":{"a":0,"k":0,"ix":6},"sa":{"a":0,"k":0,"ix":5},"o":{"a":0,"k":100,"ix":7}}]}],"ind":4}],"v":"4.8.0","fr":60,"op":120,"ip":0,"assets":[]}